gkls.cp310-win_amd64.pyd
gkls-1.0.2.dist-info/LICENSE
gkls-1.0.2.dist-info/METADATA
gkls-1.0.2.dist-info/WHEEL
gkls-1.0.2.dist-info/top_level.txt
gkls-1.0.2.dist-info/RECORD
