Metadata-Version: 2.1
Name: gkls
Version: 1.0.2
Summary: Python wrapper for the GKLS generator of global optimization test functions (Giavano et al., 2003).
Author-email: Gaëtan Serré <gaetan.serre@ens-paris-saclay.fr>
Maintainer-email: Gaëtan Serré <gaetan.serre@ens-paris-saclay.fr>
License: GNU GENERAL PUBLIC LICENSE
Project-URL: Repository, https://github.com/gaetanserre/pyGKLS
License-File: LICENSE
Requires-Dist: Cython>=3.0.11
